Metadata-Version: 2.1
Name: marinvaders
Version: 0.4.0
Summary: The marinvaders (Marine Invaders) is tool to process data on marine invasive species from existing databases
Home-page: https://gitlab.com/dlab-indecol/marinvaders
Author: Radek Lonka
Author-email: radek.lonka@ntnu.no
License: GNU GPLv3
Classifier: License :: OSI Approved :: GNU General Public License v3 (GPLv3)
Classifier: Programming Language :: Python :: 3.7
Classifier: Programming Language :: Python :: 3.8
Classifier: Programming Language :: Python :: 3.9
Classifier: Programming Language :: Python :: 3 :: Only
Classifier: Development Status :: 4 - Beta
Classifier: Environment :: Console
Classifier: Intended Audience :: End Users/Desktop
Classifier: Intended Audience :: Developers
Classifier: Intended Audience :: Science/Research
Classifier: Operating System :: MacOS :: MacOS X
Classifier: Operating System :: Microsoft :: Windows
Classifier: Operating System :: POSIX
Classifier: Programming Language :: Python
Classifier: Topic :: Scientific/Engineering
Classifier: Topic :: Utilities
Requires-Python: >=3.7.0
License-File: LICENSE
